{
  "id": "71658876201",
  "name": "texas-school-grades",
  "pageTitle": "See how Texas schools graded, A-F | Dallas News",
  "shareTitle": "See how Texas schools graded in the state’s new campus-level accountability system",
  "shareText": "Texas campuses received their first round of letter grades. More than half received an A or B. See how your school scored.",
  "tweetText": "Texas campuses received their first round of letter grades. More than half received an A or B. See how your school scored.",
  "publishYear": 2019,
  "publishDate": "2019-09-16T00:00:00Z",
  "url": "https://interactives.dallasnews.com/2019/texas-school-grades/",
  "authors": [
    "Taylor Johnston"
  ],
  "desk": "Education",
  "section": "Education",
  "keywords": [
    "Education",
    "Texas Eduation Agency",
    "Texas",
    "Texas school grades",
    "Texas school district grades",
    "Texas Legislature",
    "News",
    "Dallas ISD",
    "Dallas Independent School District",
    "elementary school",
    "middle school",
    "high school",
    "charter school",
    "interactives",
    "dallas",
    "dallas news",
    "dfw news",
    "dallas newspaper",
    "dallas morning news",
    "dallas morning news newspaper"
  ],
  "imgURL": "https://interactives.dallasnews.com/2019/texas-school-grades/images/_share.jpg",
  "imgWidth": "1200",
  "imgHeight": "630",
  "sectionTwitter": "dallasnews",
  "authorTwitter": "TF_Johnston",
  "authorFBProfile": ""
}
